LICENSE
anfis_toolbox/__init__.py
anfis_toolbox/builders.py
anfis_toolbox/classifier.py
anfis_toolbox/clustering.py
anfis_toolbox/config.py
anfis_toolbox/estimator_utils.py
anfis_toolbox/layers.py
anfis_toolbox/logging_config.py
anfis_toolbox/losses.py
anfis_toolbox/membership.py
anfis_toolbox/metrics.py
anfis_toolbox/model.py
anfis_toolbox/py.typed
anfis_toolbox/regressor.py
anfis_toolbox/optim/__init__.py
anfis_toolbox/optim/_utils.py
anfis_toolbox/optim/adam.py
anfis_toolbox/optim/base.py
anfis_toolbox/optim/hybrid.py
anfis_toolbox/optim/hybrid_adam.py
anfis_toolbox/optim/pso.py
anfis_toolbox/optim/rmsprop.py
anfis_toolbox/optim/sgd.py
docs/assets/logo.svg
anfis_toolbox-0.2.1.dist-info/METADATA
anfis_toolbox-0.2.1.dist-info/WHEEL
anfis_toolbox-0.2.1.dist-info/licenses/LICENSE
anfis_toolbox-0.2.1.dist-info/RECORD
