Metadata-Version: 2.4
Name: anfis-toolbox
Version: 0.2.1
Summary: ANFIS Toolbox is a comprehensive Python library for creating, training, and deploying Adaptive Neuro-Fuzzy Inference Systems (ANFIS). It provides an intuitive API that makes fuzzy neural networks accessible to both beginners and experts.
Project-URL: Homepage, https://github.com/dcruzf/anfis-toolbox
Project-URL: Documentation, https://dcruzf.github.io/anfis-toolbox/
Project-URL: Source, https://github.com/dcruzf/anfis-toolbox
Project-URL: Tracker, https://github.com/dcruzf/anfis-toolbox/issues
Project-URL: DOI, https://doi.org/10.5281/zenodo.17437178
Author-email: Daniel França <daniel@ci.ufpb.br>
License: MIT
License-File: LICENSE
Keywords: anfis,explainable ai,fuzzy logic,machine learning,neuro-fuzzy
Classifier: Development Status :: 5 - Production/Stable
Classifier: Intended Audience :: Science/Research
Classifier: License :: OSI Approved :: MIT License
Classifier: Operating System :: OS Independent
Classifier: Programming Language :: Python
Classifier: Programming Language :: Python :: 3
Classifier: Programming Language :: Python :: 3.10
Classifier: Programming Language :: Python :: 3.11
Classifier: Programming Language :: Python :: 3.12
Classifier: Programming Language :: Python :: 3.13
Classifier: Programming Language :: Python :: 3.14
Classifier: Topic :: Scientific/Engineering :: Artificial Intelligence
Classifier: Topic :: Scientific/Engineering :: Mathematics
Requires-Python: >=3.10
Requires-Dist: numpy<3.0,>=1.23
Provides-Extra: dev
Requires-Dist: bandit>=1.7.9; extra == 'dev'
Requires-Dist: hatch>=1.16.2; extra == 'dev'
Requires-Dist: mypy>=1.10.0; extra == 'dev'
Requires-Dist: pre-commit; extra == 'dev'
Requires-Dist: pytest>=8.4.1; extra == 'dev'
Requires-Dist: ruff; extra == 'dev'
Requires-Dist: scikit-learn>=1.7.2; extra == 'dev'
